{
    "marco": {
        "debug": false,
        "integrity": false,
        "base_size": 8841823,
        "dummy_size": 64,
        "real_bucket_size": 32,
        "evict_rate": 36,
        "num_levels": 19,
        "oram_cached_levels": 6,
        "block_size": 898,
        "large_number": 1000000,
        "use_oram": true,
        "buckets_path": "/data/oram_data/marco/R128_L100_PQ64/buckets.bin",
        "graph_cache_path": "/data/oram_data/marco/R128_L100_PQ64/graph_cache.bin",
        "hash_path": "/data/oram_data/marco/R128_L100_PQ64/hash.bin",
        "metadata_path": "/data/oram_data/marco/R128_L100_PQ64/metadata.bin",
        "pos_map_path": "/data/oram_data/marco/R128_L100_PQ64/position_map.bin",
        "block_map_path": "/data/oram_data/marco/R128_L100_PQ64/block_mapping.bin",
        "--data_type": "float",
        "--dist_fn": "l2",
        "dim": 768,
        "-K": 10,
        "--num_nodes_to_cache": 0,
        "--query_nums": 50,
        "M": 128,
        "-W": 16,
        "-L": 100,
        "--search_io_limit": 8,
        "--data_path": "/data/data/datasets/marco/base.fbin",
        "--index_path_prefix": "/data/data/index/marco/disk_index_marco_base_R128_L100_A1.2",
        "base_path": "/data/data/datasets/marco/base.fvecs",
        "--query_file": "/data/data/datasets/marco/marco_query.fbin",
        "--gt_file": "/data/data/datasets/marco/marco_query_base_gt100",
        "--result_path": "/data/results/trip"
    }
}
